unified_database/__init__.py
unified_database/mongo_crud.py
unified_database-0.0.6.dist-info/METADATA
unified_database-0.0.6.dist-info/WHEEL
unified_database-0.0.6.dist-info/top_level.txt
unified_database-0.0.6.dist-info/RECORD
